{
    "quiz1": [
        {
            "id": 1,
            "question": "Câu 1: Theo WHO, 2 thông tin tối thiểu để nhận diện chính xác người bệnh trước khi thực hiện dịch vụ y tế là gì?",
            "options": [
                "A. Số giường và Số phòng.",
                "B. Họ tên đầy đủ và Số bệnh án/Mã người bệnh (hoặc ngày tháng năm sinh).",
                "C. Họ tên đầy đủ và Chẩn đoán bệnh.",
                "D. Tên khoa phòng và Tên bác sĩ điều trị."
            ],
            "answer": [
                1
            ]
        },
        {
            "id": 2,
            "question": "Câu 2: Khi phát hiện một sự cố y khoa suýt soát (Near-miss - chưa chạm đến người bệnh), hành động đúng của điều dưỡng là gì?",
            "options": [
                "A. Bỏ qua vì người bệnh chưa bị tổn thương.",
                "B. Chỉ nói miệng với đồng nghiệp trong ca trực.",
                "C. Ghi nhận và báo cáo tự nguyện theo quy trình quản lý sự cố y khoa của bệnh viện.",
                "D. Giấu kín để tránh ảnh hưởng đến thi đua của khoa."
            ],
            "answer": [
                2
            ]
        },
        {
            "id": 3,
            "question": "Câu 3: Quy trình \"5 đúng\" khi cho người bệnh dùng thuốc bao gồm các yếu tố nào?",
            "options": [
                "A. Đúng người bệnh, đúng thuốc, đúng liều, đúng đường dùng, đúng thời gian.",
                "B. Đúng người bệnh, đúng thuốc, đúng liều, đúng giá tiền, đúng thời gian.",
                "C. Đúng người bệnh, đúng phòng, đúng thuốc, đúng đường dùng, đúng thời gian.",
                "D. Đúng giường, đúng thuốc, đúng liều, đúng bác sĩ chỉ định, đúng thời gian."
            ],
            "answer": [
                0
            ]
        },
        {
            "id": 4,
            "question": "Câu 4: Thời điểm nào sau đây KHÔNG thuộc \"5 thời điểm vệ sinh tay\" bảo vệ an toàn cho người bệnh?",
            "options": [
                "A. Trước khi tiếp xúc với người bệnh.",
                "B. Trước khi làm thủ thuật vô khuẩn.",
                "C. Sau khi tiếp xúc với người bệnh.",
                "D. Trước khi điều dưỡng bước vào ca trực."
            ],
            "answer": [
                3
            ]
        },
        {
            "id": 5,
            "question": "Câu 5: Thang đo MORSE thường được điều dưỡng sử dụng trên lâm sàng để đánh giá nguy cơ nào của người bệnh?",
            "options": [
                "A. Nguy cơ loét tỳ đè.",
                "B. Nguy cơ té ngã.",
                "C. Nguy cơ suy dinh dưỡng.",
                "D. Nguy cơ nhiễm khuẩn huyết."
            ],
            "answer": [
                1
            ]
        },
        {
            "id": 6,
            "question": "Câu 6: Biện pháp nào là quan trọng nhất để phòng ngừa té ngã cho người bệnh có nguy cơ cao tại giường?",
            "options": [
                "A. Luôn kéo cao thanh chắn hai bên giường bệnh.",
                "B. Cho người bệnh uống thuốc an thần.",
                "C. Yêu cầu người nhà ngồi ôm người bệnh 24/24.",
                "D. Tắt hết đèn trong phòng bệnh vào ban đêm."
            ],
            "answer": [
                0
            ]
        },
        {
            "id": 7,
            "question": "Câu 7: Khi thực hiện y lệnh thuốc qua đường tiêm tĩnh mạch, điều dưỡng phải thực hiện kỹ thuật nào để đảm bảo an toàn tối đa?",
            "options": [
                "A. Tiêm thật nhanh để người bệnh đỡ đau.",
                "B. Hút thuốc xong tiêm ngay không cần kiểm tra lại danh tính.",
                "C. Thực hiện \"3 tra, 5 đối\" và kiểm tra sự lưu thông của đường truyền trước khi bơm thuốc.",
                "D. Nhờ người nhà giữ hộ kim tiêm."
            ],
            "answer": [
                2
            ]
        },
        {
            "id": 8,
            "question": "Câu 8: Nhãn thuốc có cảnh báo chữ \"ĐỘC\" hoặc thuốc có nguy cơ cao (High-alert medications) cần được lưu trữ như thế nào tại tủ trực khoa?",
            "options": [
                "A. Để chung với các loại dịch truyền thông thường.",
                "B. Có khu vực lưu trữ riêng, dán nhãn cảnh báo rõ ràng và bảo quản theo quy định.",
                "C. Để ở bàn hành chính cho dễ lấy.",
                "D. Cho vào tủ cá nhân của điều dưỡng trưởng."
            ],
            "answer": [
                1
            ]
        },
        {
            "id": 9,
            "question": "Câu 9: Khi phát hiện đường truyền dịch của người bệnh bị phồng (thoát mạch), hành động đầu tiên của điều dưỡng là gì?",
            "options": [
                "A. Chườm nóng ngay lập tức.",
                "B. Khóa dịch truyền và ngừng tiêm/truyền ngay lập tức.",
                "C. Rút kim ra ngay và sát khuẩn mạnh.",
                "D. Tăng tốc độ truyền để thuốc tan đi."
            ],
            "answer": [
                1
            ]
        },
        {
            "id": 10,
            "question": "Câu 10: Vòng nhận diện người bệnh (vòng đeo tay) màu ĐỎ thường được quy ước dùng cho đối tượng nào tại các bệnh viện?",
            "options": [
                "A. Người bệnh chuẩn bị ra viện.",
                "B. Người bệnh có tiền sử dị ứng (thuốc, thức ăn...).",
                "C. Người bệnh có nguy cơ té ngã.\nd. Người bệnh điều trị tự nguyện."
            ],
            "answer": [
                1
            ]
        },
        {
            "id": 11,
            "question": "Câu 11: Sự cố y khoa (Adverse Event - AE) được định nghĩa là gì?",
            "options": [
                "A. Là các tai biến do người bệnh tự gây ra.",
                "B. Là các tác hại liên quan đến chẩn đoán, điều trị, chăm sóc y tế nhưng không do diễn tiến bệnh lý tự nhiên của người bệnh.",
                "C. Là các xung đột, cãi vã giữa nhân viên y tế và người nhà.",
                "D. Là các lỗi hành chính trong khâu thu tiền viện phí."
            ],
            "answer": [
                1
            ]
        },
        {
            "id": 12,
            "question": "Câu 12: Khi người bệnh phàn nàn rằng \"Thuốc này nhìn không giống loại tôi uống hôm qua\", điều dưỡng nên làm gì?",
            "options": [
                "A. Bảo người bệnh cứ uống đi vì bác sĩ đã kê đơn thì không sai.",
                "B. Dừng lại, kiểm tra lại hồ sơ bệnh án, đơn thuốc và nhãn thuốc trước khi cho người bệnh uống.",
                "C. Trách mắng người bệnh hay thắc mắc.",
                "D. Đổi sang loại thuốc khác ngay lập tức mà không cần hỏi lại bác sĩ."
            ],
            "answer": [
                1
            ]
        },
        {
            "id": 13,
            "question": "Câu 13: Mục đích chính của việc báo cáo sự cố y khoa trong bệnh viện là gì?",
            "options": [
                "A. Để tìm ra người làm sai và xử phạt nghiêm khắc.",
                "B. Để cắt thi đua và trừ lương nhân viên vi phạm.",
                "C. Để phân tích nguyên nhân hệ thống, học tập từ sai lầm và cải tiến quy trình nhằm ngăn ngừa tái diễn.",
                "D. Để làm tư liệu nộp cho cơ quan công an khi có khiếu kiện."
            ],
            "answer": [
                2
            ]
        },
        {
            "id": 14,
            "question": "Câu 14: Trước khi đưa người bệnh đi phẫu thuật/thủ thuật, điều dưỡng khoa lâm sàng KHÔNG cần bàn giao nội dung nào sau đây cho điều dưỡng phòng mổ?",
            "options": [
                "A. Hồ sơ bệnh án đầy đủ và các xét nghiệm, phim ảnh liên quan.",
                "B. Tình trạng thực tế của người bệnh (tri giác, sinh hiệu, vùng mổ đã đánh dấu).",
                "C. Danh tính chính xác qua vòng nhận diện và cam kết phẫu thuật.",
                "D. Hoàn cảnh kinh tế gia đình của người bệnh."
            ],
            "answer": [
                3
            ]
        },
        {
            "id": 15,
            "question": "Câu 15: Khi thực hiện y lệnh miệng (trong trường hợp cấp cứu khẩn cấp), điều dưỡng cần tuân thủ nguyên tắc an toàn nào?",
            "options": [
                "A. Thực hiện ngay lập tức mà không cần nhắc lại y lệnh.",
                "B. Lặp lại y lệnh (Read-back) để bác sĩ xác nhận đúng trước khi thực hiện, sau đó ghi và ký bổ sung vào bệnh án khi qua cơn nguy kịch.",
                "C. Từ chối thực hiện vì chưa có chữ ký trong bệnh án.",
                "D. Nhờ một đồng nghiệp khác nghe hộ."
            ],
            "answer": [
                1
            ]
        },
        {
            "id": 16,
            "question": "Câu 16: Việc đánh giá nguy cơ loét tỳ đè ở người bệnh nằm bất động lâu ngày thường dựa trên thang điểm nào?",
            "options": [
                "A. Thang điểm Glasgow.",
                "B. Thang điểm Braden.",
                "C. Thang điểm VAS.",
                "D. Thang điểm APACH",
                "E."
            ],
            "answer": [
                1
            ]
        },
        {
            "id": 17,
            "question": "Câu 17: Để đảm bảo an toàn khi vận chuyển người bệnh nặng bằng băng ca/xe đẩy, tư thế của điều dưỡng đứng ở vị trí nào là đúng quy chuẩn?",
            "options": [
                "A. Đi phía sau xe đẩy để đẩy xe đi tới.",
                "B. Đi phía đầu người bệnh để vừa đẩy/kéo vừa theo dõi sát nét mặt và tri giác người bệnh.",
                "C. Đi bên cạnh để nói chuyện với người bệnh.",
                "D. Đi phía trước kéo xe, quay lưng lại với người bệnh."
            ],
            "answer": [
                1
            ]
        },
        {
            "id": 18,
            "question": "Câu 18: Việc \"Đánh dấu vùng mổ\" áp dụng đối với các trường hợp phẫu thuật nào?",
            "options": [
                "A. Tất cả các phẫu thuật ở cơ quan có tính chất đối xứng (trái/phải), nhiều vị trí, nhiều tầng.",
                "B. Chỉ áp dụng cho phẫu thuật thẩm mỹ.",
                "C. Chỉ áp dụng khi người bệnh yêu cầu.",
                "D. Phẫu thuật ruột thừa cấp."
            ],
            "answer": [
                0
            ]
        },
        {
            "id": 19,
            "question": "Câu 19: Trong quy trình truyền máu an toàn tại giường, điều dưỡng phải thực hiện việc định nhóm máu gì ngay trước khi cắm dây truyền vào người bệnh?",
            "options": [
                "A. Không cần định lại nhóm máu nếu túi máu đã có nhãn.",
                "B. Định lại nhóm máu hệ ABO của người bệnh và của túi máu ngay tại giường (làm kỹ thuật bản đá).",
                "C. Nhờ người nhà xác nhận lại nhóm máu của người bệnh.",
                "D. Gọi điện hỏi khoa Huyết học xem có đúng không."
            ],
            "answer": [
                1
            ]
        },
        {
            "id": 20,
            "question": "Câu 20: Khi một thiết bị y tế (như máy truyền dịch, máy theo dõi Monitor) đang dùng cho người bệnh bỗng nhiên báo lỗi phát tiếng kêu liên tục, điều dưỡng cần làm gì?",
            "options": [
                "A. Bật nút tắt tiếng chuông cảnh báo và kệ cho máy chạy tiếp.",
                "B. Đánh giá ngay tình trạng người bệnh, tạm ngừng sử dụng máy lỗi, chuyển sang thiết bị dự phòng thay thế và báo phòng Vật tư trang thiết bị sửa chữa.",
                "C. Rút phích cắm điện ra rồi cắm lại xem có hết lỗi không.",
                "D. Đợi đến hết ca trực rồi bàn giao cho ca sau xử lý.\nĐáp án: B\nPHẦN 2: KIỂM SOÁT NHIỄM KHUẨN (Câu 21 - 40)"
            ],
            "answer": [
                1
            ]
        },
        {
            "id": 21,
            "question": "Câu 21: Thời gian chà sát tay tối thiểu bằng dung dịch chứa cồn theo quy trình rửa tay thường quy của Bộ Y tế là bao lâu?",
            "options": [
                "A. 10 - 15 giây.",
                "B. 20 - 30 giây.",
                "C. 1 phút.",
                "D. 2 phút."
            ],
            "answer": [
                1
            ]
        },
        {
            "id": 22,
            "question": "Câu 22: Chất thải lây nhiễm không sắc nhọn (như bông băng dính máu, dịch tiết) phải được thu gom vào túi/thùng màu gì?",
            "options": [
                "A. Màu xanh.",
                "B. Màu vàng.",
                "C. Màu đen.",
                "D. Màu trắng."
            ],
            "answer": [
                1
            ]
        },
        {
            "id": 23,
            "question": "Câu 23: Theo quy định về Phòng ngừa chuẩn, điều dưỡng cần mang găng tay khi nào?",
            "options": [
                "A. Khi tiếp xúc với da lành của người bệnh.",
                "B. Khi phát thuốc viên cho người bệnh.",
                "C. Khi dự kiến tay có thể tiếp xúc với máu, dịch cơ thể, niêm mạc hoặc da không lành lặn của người bệnh.",
                "D. Trong suốt thời gian làm việc tại khoa phòng."
            ],
            "answer": [
                2
            ]
        },
        {
            "id": 24,
            "question": "Câu 24: Loại chất thải nào sau đây được phân loại vào nhóm chất thải nguy hại không lây nhiễm (thu gom vào túi/thùng màu đen)?",
            "options": [
                "A. Kim tiêm, mảnh thủy tinh sắc nhọn dính máu.",
                "B. Vỏ lọ thuốc nát, phim X-quang hỏng, chất hóa học thải bỏ, thiết bị y tế hỏng chứa thủy ngân.",
                "C. Rác thải sinh hoạt của người nhà người bệnh (hộp cơm, vỏ hoa quả).",
                "D. Mô, bộ phận cơ thể người thải bỏ."
            ],
            "answer": [
                1
            ]
        },
        {
            "id": 25,
            "question": "Câu 25: Hộp kháng thủng (thùng/hộp màu vàng có thành cứng) dùng để thu gom loại chất thải nào?",
            "options": [
                "A. Bông băng thấm máu.",
                "B. Các loại chất thải sắc nhọn lây nhiễm (kim tiêm, lưỡi dao mổ, mảnh thủy tinh vỡ dính máu).",
                "C. Chai lọ thủy tinh đựng dịch truyền chưa dính máu.",
                "D. Khẩu trang y tế đã qua sử dụng."
            ],
            "answer": [
                1
            ]
        },
        {
            "id": 26,
            "question": "Câu 26: Theo quy trình rửa tay thường quy của Bộ Y tế, có bao nhiêu bước chà tay kỹ thuật?",
            "options": [
                "A. 5 bước.",
                "B. 6 bước.",
                "C. 7 bước.",
                "D. 8 bước."
            ],
            "answer": [
                1
            ]
        },
        {
            "id": 27,
            "question": "Câu 27: Sau khi tiêm thuốc cho người bệnh, điều dưỡng cần xử lý kim tiêm như thế nào?",
            "options": [
                "A. Dùng hai tay đậy lại nắp kim tiêm rồi bỏ vào thùng rác.",
                "B. Dùng kỹ thuật một tay (múc nắp kim) nếu bắt buộc phải đậy, hoặc bỏ ngay kim tiêm vào hộp kháng thủng mà không cần đậy nắp kim.",
                "C. Bẻ cong kim tiêm trước khi bỏ vào thùng rác.",
                "D. Để trên khay tiêm đem về buồng hành chính xử lý sau."
            ],
            "answer": [
                1
            ]
        },
        {
            "id": 28,
            "question": "Câu 28: Khẩu trang N95 hoặc tương đương được chỉ định bắt buộc cho điều dưỡng khi chăm sóc người bệnh lây truyền qua đường nào?",
            "options": [
                "A. Đường tiếp xúc (Contact).",
                "B. Đường giọt bắn (Droplet).",
                "C. Đường không khí (Airborne - như Lao phổi, Sởi, Thủy đậu).",
                "D. Đường tiêu hóa."
            ],
            "answer": [
                2
            ]
        },
        {
            "id": 29,
            "question": "Câu 29: Rác thải sinh hoạt thông thường của người bệnh (không liên quan đến dịch tiết lây nhiễm) được thu gom vào túi màu gì?",
            "options": [
                "A. Màu vàng.",
                "B. Màu xanh.",
                "C. Màu đen.",
                "D. Màu trắng."
            ],
            "answer": [
                1
            ]
        },
        {
            "id": 30,
            "question": "Câu 30: Phương pháp khử khuẩn tay bằng dung dịch sát khuẩn chứa cồn KHÔNG được áp dụng trong trường hợp nào?",
            "options": [
                "A. Sau khi tháo găng tay y tế.",
                "B. Khi tay nhìn thấy rõ có vết bẩn bằng mắt thường, dính máu hoặc dịch tiết.",
                "C. Trước khi thăm khám cho người bệnh tiếp theo.",
                "D. Sau khi chạm vào ga trải giường của người bệnh.\nĐáp án: B (Trường hợp này phải rửa tay bằng nước và xà phòng)."
            ],
            "answer": [
                1
            ]
        },
        {
            "id": 31,
            "question": "Câu 31: Dụng cụ y tế phân loại vào nhóm \"Dụng cụ thiết yếu\" (Critical items - tiếp xúc trực tiếp với mô vô trùng hoặc mạch máu) yêu cầu xử lý ở mức độ nào?",
            "options": [
                "A. Chỉ cần làm sạch bằng nước.",
                "B. Khử khuẩn mức độ trung bình.",
                "C. Khử khuẩn mức độ cao.",
                "D. Tiệt khuẩn (Sterilization)."
            ],
            "answer": [
                3
            ]
        },
        {
            "id": 32,
            "question": "Câu 32: Dụng cụ nào sau đây thuộc nhóm dụng cụ \"Không thiết yếu\" (Non-critical items - chỉ tiếp xúc với da lành)?",
            "options": [
                "A. Dao mổ, kim chọc dò.",
                "B. Ống nghe, bao đo huyết áp, nhiệt kế áp da.",
                "C. Ống nội khí quản, ống soi dạ dày.",
                "D. Kéo phẫu thuật."
            ],
            "answer": [
                1
            ]
        },
        {
            "id": 33,
            "question": "Câu 33: Khi thu gom đồ vải nhiễm khuẩn (dính máu/dịch tiết) tại buồng bệnh, điều dưỡng cần tuân thủ nguyên tắc nào?",
            "options": [
                "A. Giũ mạnh đồ vải để rũ bụi bẩn trước khi cuộn lại.",
                "B. Cho đồ vải nhiễm khuẩn vào túi màu vàng (có biểu tượng nguy hại sinh học), không giũ, cuộn phần bẩn vào trong và buộc kín miệng túi tại chỗ.",
                "C. Gom chung với đồ vải sạch để tiết kiệm túi.",
                "D. Mang trực tiếp đồ vải bẩn bằng tay trần xuống nhà giặt."
            ],
            "answer": [
                1
            ]
        },
        {
            "id": 34,
            "question": "Câu 34: Tần suất vệ sinh và khử khuẩn các bề mặt tiếp xúc thường xuyên tại buồng bệnh (như nút bấm, tay nắm cửa, thành giường) tối thiểu là bao nhiêu?",
            "options": [
                "A. 1 tuần 1 lần.",
                "B. Mỗi ngày ít nhất 1-2 lần (hoặc ngay khi có dính máu/dịch tiết).",
                "C. Chỉ làm khi người bệnh ra viện.",
                "D. 1 tháng 1 lần."
            ],
            "answer": [
                1
            ]
        },
        {
            "id": 35,
            "question": "Câu 35: Khi bị kim tiêm hoặc vật sắc nhọn dính máu người bệnh đâm vào tay, xử trí ban đầu đúng nhất của điều dưỡng là gì?",
            "options": [
                "A. Bóp nặn thật mạnh cho máu ra hết rồi ngâm vào cồn 90 độ.",
                "B. Để vết thương dưới vòi nước chảy, để máu tự chảy ra (không nặn bóp), rửa sạch bằng xà phòng và nước sạch, sau đó sát khuẩn bằng cồn hoặc dung dịch sát khuẩn phù hợp.",
                "C. Lấy lưỡi dao rạch rộng vết thương để rửa.",
                "D. Giấu kín không báo cho ai vì sợ bị kỳ thị."
            ],
            "answer": [
                1
            ]
        },
        {
            "id": 36,
            "question": "Câu 36: Sau bước xử trí ban đầu khi bị phơi nhiễm với máu/dịch cơ thể của người bệnh, việc tiếp theo điều dưỡng cần làm là gì?",
            "options": [
                "A. Tự ra hiệu thuốc mua thuốc uống.",
                "B. Báo cáo ngay cho Điều dưỡng trưởng/Bác sĩ phụ trách, lập biên bản phơi nhiễm và đến khoa Kiểm soát nhiễm khuẩn/Y tế cơ quan để được đánh giá nguy cơ và điều trị dự phòng (PEP) nếu cần.",
                "C. Xin nghỉ làm vài ngày để theo dõi.",
                "D. Yêu cầu người bệnh bồi thường tiền mặt."
            ],
            "answer": [
                1
            ]
        },
        {
            "id": 37,
            "question": "Câu 37: Nồng độ dung dịch Cloramin B thường dùng để lau khử khuẩn bề mặt nền nhà buồng bệnh định kỳ hàng ngày là bao nhiêu?",
            "options": [
                "A. 0,05% đến 0,1% clo hoạt tính.",
                "B. 0,5% clo hoạt tính.",
                "C. 1% clo hoạt tính.",
                "D. 5% clo hoạt tính."
            ],
            "answer": [
                0
            ]
        },
        {
            "id": 38,
            "question": "Câu 38: Nhiễm khuẩn bệnh viện (Nhiễm khuẩn liên quan đến chăm sóc y tế) được định nghĩa là gì?",
            "options": [
                "A. Là nhiễm khuẩn mà người bệnh đã mắc phải trước khi vào viện điều trị.",
                "B. Là các nhiễm khuẩn xuất hiện ở người bệnh sau khi nhập viện từ 48 giờ trở đi và không ở trong giai đoạn ủ bệnh tại thời điểm nhập viện.",
                "C. Là bệnh truyền nhiễm lây từ người bệnh này sang người bệnh khác ở ngoài cộng đồng.",
                "D. Là tình trạng dị ứng thuốc điều trị tại bệnh viện."
            ],
            "answer": [
                1
            ]
        },
        {
            "id": 39,
            "question": "Câu 39: Loại nhiễm khuẩn bệnh viện nào chiếm tỷ lệ cao nhất và thường liên quan trực tiếp đến các thủ thuật xâm lấn của điều dưỡng?",
            "options": [
                "A. Nhiễm khuẩn vết mổ, nhiễm khuẩn huyết do đường truyền, nhiễm khuẩn tiết niệu do đặt sonde tiểu, viêm phổi liên quan đến thở máy.",
                "B. Nhiễm khuẩn da thông thường.",
                "C. Viêm mũi họng cấp tính.",
                "D. Nhiễm giun sán."
            ],
            "answer": [
                0
            ]
        },
        {
            "id": 40,
            "question": "Câu 40: Khi thực hiện kỹ thuật thay băng vết mổ cho người bệnh, điều dưỡng cần tuân thủ nguyên tắc vô khuẩn nào sau đây?",
            "options": [
                "A. Thay băng vết bẩn trước, vết sạch sau.",
                "B. Thay băng vết sạch trước, vết bẩn sau; sử dụng bộ dụng cụ vô khuẩn riêng cho từng người bệnh.",
                "C. Dùng chung một panh (kẹp) cho tất cả người bệnh trong phòng để tiết kiệm dụng cụ.",
                "D. Không cần mang khẩu trang khi thay băng.\nĐáp án: B\nPHẦN 3: QUY CHẾ CHUYÊN MÔN & PHÁP LUẬT (Câu 41 - 60)"
            ],
            "answer": [
                1
            ]
        },
        {
            "id": 41,
            "question": "Câu 41: Theo Thông tư 31/2021/TT-BYT quy định về công tác điều dưỡng trong bệnh viện, nhận định lâm sàng và phân cấp chăm sóc người bệnh do ai thực hiện?",
            "options": [
                "A. Do Hộ lý thực hiện dựa trên tình trạng vệ sinh của người bệnh.",
                "B. Bác sĩ điều trị phối hợp với Điều dưỡng viên thực hiện nhận định và phân cấp chăm sóc phù hợp.",
                "C. Do người bệnh tự lựa chọn gói chăm sóc.",
                "D. Do Điều dưỡng trưởng khối quyết định từ xa."
            ],
            "answer": [
                1
            ]
        },
        {
            "id": 42,
            "question": "Câu 42: Người bệnh được phân cấp \"Chăm sóc cấp I\" theo Thông tư 31/2021/TT-BYT bao gồm đối tượng nào?",
            "options": [
                "A. Người bệnh trong tình trạng ổn định, tự thực hiện được các hoạt động sinh hoạt hàng ngày.",
                "B. Người bệnh trong tình trạng nguy kịch, có nguy cơ đe dọa tính mạng; hoặc người bệnh nằm bất động, phụ thuộc hoàn toàn vào sự theo dõi, chăm sóc của nhân viên y tế.",
                "C. Người bệnh chuẩn bị ra viện.",
                "D. Người bệnh điều trị ngoại trú tại khoa Khám bệnh."
            ],
            "answer": [
                1
            ]
        },
        {
            "id": 43,
            "question": "Câu 43: Đối với người bệnh phân cấp \"Chăm sóc cấp II\", điều dưỡng có nhiệm vụ gì?",
            "options": [
                "A. Bỏ mặc người bệnh tự làm hết mọi việc.",
                "B. Theo dõi, hỗ trợ người bệnh thực hiện các hoạt động sinh hoạt hàng ngày khi cần thiết; thực hiện các can thiệp điều dưỡng và y lệnh điều trị.",
                "C. Phải ngồi túc trực liên tục bên giường bệnh không được rời đi.",
                "D. Giao hoàn toàn cho học sinh thực tập chăm sóc."
            ],
            "answer": [
                1
            ]
        },
        {
            "id": 44,
            "question": "Câu 44: Việc ghi chép Phiếu theo dõi và chăm sóc điều dưỡng trong hồ sơ bệnh án phải đảm bảo các nguyên tắc nào?",
            "options": [
                "A. Ghi trước khi thực hiện để tiết kiệm thời gian.",
                "B. Ghi trung thực, chính xác, khách quan, kịp thời ngay sau khi thực hiện can thiệp; chữ viết rõ ràng, không viết tắt từ ngữ tự chế, ký và ghi rõ họ tên.",
                "C. Cuối ca trực nhớ gì ghi nấy, có thể tẩy xóa bằng bút xóa nếu viết sai.",
                "D. Chỉ cần ghi khi người bệnh có diễn biến nặng, ngày bình thường không cần ghi."
            ],
            "answer": [
                1
            ]
        },
        {
            "id": 45,
            "question": "Câu 45: Khi phát hiện chữ viết của bác sĩ trong tờ y lệnh thuốc bị mờ, nhầm lẫn hoặc không rõ ràng, điều dưỡng cần làm gì?",
            "options": [
                "A. Tự đoán ý bác sĩ để đi lấy thuốc cho kịp thời gian.",
                "B. Từ chối thực hiện và không báo cho ai.",
                "C. Liên hệ ngay với bác sĩ ra y lệnh để xác nhận lại thông tin chính xác trước khi thực hiện.",
                "D. Nhờ một điều dưỡng khác dịch hộ rồi làm theo."
            ],
            "answer": [
                2
            ]
        },
        {
            "id": 46,
            "question": "Câu 46: Thời gian tối đa để điều dưỡng hoàn thành việc ghi chép các thông số dấu hiệu sinh tồn vào mạch duy trì sau khi đo cho người bệnh là bao lâu?",
            "options": [
                "A. Để đến cuối ngày ghi một thể.",
                "B. Ghi ngay sau khi đo hoặc chậm nhất trong ca trực theo quy định của bệnh viện (trừ trường hợp cấp cứu phải ghi ngay).",
                "C. Bàn giao cho ca trực sau ghi hộ.",
                "D. Chỉ cần báo miệng, không cần ghi vào mạch duy trì."
            ],
            "answer": [
                1
            ]
        },
        {
            "id": 47,
            "question": "Câu 47: Theo Luật Khám bệnh, chữa bệnh hiện hành, hành vi nào sau đây bị nghiêm cấm đối với người hành nghề?",
            "options": [
                "A. Giải thích tình trạng bệnh cho người nhà người bệnh khi được phép.",
                "B. Từ chối khám bệnh, chữa bệnh trong trường hợp tiên lượng bệnh vượt quá khả năng hoặc trái quy định pháp luật nhưng phải giới thiệu người bệnh đến cơ sở khác.",
                "C. Thu thêm các khoản chi phí ngoài quy định của pháp luật và của bệnh viện; nhận quà, tiền trục lợi từ người bệnh.",
                "D. Tham gia các lớp đào tạo liên tục cập nhật kiến thức y khoa."
            ],
            "answer": [
                2
            ]
        },
        {
            "id": 48,
            "question": "Câu 48: Khi người bệnh chuyển khoa, điều dưỡng khoa đi có trách nhiệm bàn giao những gì cho điều dưỡng khoa đến?",
            "options": [
                "A. Chỉ cần đưa người bệnh sang rồi về.",
                "B. Bàn giao trực tiếp tại giường: Người bệnh (danh tính, tình trạng hiện tại), Hồ sơ bệnh án, thuốc và các vật dụng y tế đi kèm (nếu có), ký biên bản bàn giao.",
                "C. Gửi hồ sơ qua hộ lý mang sang trước, người bệnh sang sau.",
                "D. Chỉ cần gọi điện thoại thông báo."
            ],
            "answer": [
                1
            ]
        },
        {
            "id": 49,
            "question": "Câu 49: Trong quy trình bàn giao ca trực (giao ban ca), nội dung nào là quan trọng nhất cần được bàn giao chi tiết giữa hai kíp trực?",
            "options": [
                "A. Số lượng người bệnh ra viện trong ngày.",
                "B. Số lượng người bệnh nặng, người bệnh mới vào, người bệnh có chỉ định phẫu thuật/thủ thuật, các diễn biến bất thường và y lệnh còn lại chưa thực hiện.",
                "C. Ý kiến khen chê của người nhà về cơ sở vật chất.",
                "D. Tình hình thời tiết trong ca trực."
            ],
            "answer": [
                1
            ]
        },
        {
            "id": 50,
            "question": "Câu 50: Theo quy định, thời gian lưu trữ hồ sơ bệnh án nội trú thông thường sau khi người bệnh ra viện tối thiểu là bao nhiêu năm?",
            "options": [
                "A. 5 năm.",
                "B. 10 năm.",
                "C. 20 năm.",
                "D. 30 năm."
            ],
            "answer": [
                2
            ]
        },
        {
            "id": 51,
            "question": "Câu 51: Quyền nào sau đây KHÔNG phải là quyền của người bệnh theo Luật Khám bệnh, chữa bệnh?",
            "options": [
                "A. Quyền được tôn trọng danh dự, bảo mật thông tin riêng tư trong hồ sơ bệnh án.",
                "B. Quyền được lựa chọn người hành nghề và cơ sở khám chữa bệnh theo quy định.",
                "C. Quyền được từ chối điều trị và ra khỏi cơ sở khám chữa bệnh (trừ trường hợp bắt buộc chữa bệnh theo luật).",
                "D. Quyền được yêu cầu nhân viên y tế thực hiện các dịch vụ nằm ngoài phạm vi chuyên môn chuyên ngành của bệnh viện."
            ],
            "answer": [
                3
            ]
        },
        {
            "id": 52,
            "question": "Câu 52: Nghĩa vụ của người bệnh đối với cơ sở khám bệnh, chữa bệnh là gì?",
            "options": [
                "A. Được làm bất cứ điều gì mình thích trong khuôn viên bệnh viện.",
                "B. Chấp hành các quy định, nội quy của cơ sở khám bệnh, chữa bệnh; tôn trọng nhân viên y tế; chi trả chi phí khám chữa bệnh theo quy định.",
                "C. Tự ý thay đổi liều lượng thuốc bác sĩ đã kê đơn.",
                "D. Có quyền lăng mạ nhân viên y tế nếu không hài lòng."
            ],
            "answer": [
                1
            ]
        },
        {
            "id": 53,
            "question": "Câu 53: Phiếu công khai thuốc hàng ngày cho người bệnh cần được thực hiện khi nào?",
            "options": [
                "A. Ký công khai một lần vào ngày người bệnh ra viện.",
                "B. Công khai thuốc và vật tư y tế tiêu hao hàng ngày cho người bệnh hoặc người nhà ký xác nhận định kỳ theo quy định của bệnh viện.",
                "C. Chỉ công khai bằng miệng, không cần phiếu giấy hay ký nhận.",
                "D. Do điều dưỡng tự ký thay cho người bệnh để hoàn thiện thủ tục hành chính."
            ],
            "answer": [
                1
            ]
        },
        {
            "id": 54,
            "question": "Câu 54: Khi người bệnh xin ra viện trước thời hạn (xin về khi bệnh chưa ổn định), điều dưỡng cần hướng dẫn họ làm thủ tục gì để đảm bảo tính pháp lý?",
            "options": [
                "A. Bảo họ cứ tự ý thu dọn quần áo ra về.",
                "B. Giải thích rõ nguy cơ, yêu cầu người bệnh hoặc người đại diện hợp pháp viết đơn xin cam kết tự chịu trách nhiệm ký vào hồ sơ bệnh án, sau đó báo bác sĩ hoàn thiện thủ tục hành chính.",
                "C. Gọi bảo vệ giữ người bệnh lại không cho về.",
                "D. Bắt người bệnh nộp phạt hành chính."
            ],
            "answer": [
                1
            ]
        },
        {
            "id": 55,
            "question": "Câu 55: Khi ghi sai thông tin trên Phiếu điều dưỡng bằng giấy, cách sửa đúng luật và quy chế là gì?",
            "options": [
                "A. Dùng bút xóa màu trắng che kín vết sai rồi viết đè lên.",
                "B. Dùng dao lam cạo sạch chữ sai.",
                "C. Gạch một đường ngang chữ viết sai (sao cho vẫn đọc được chữ cũ), viết chữ đúng lên phía trên hoặc bên cạnh và ký xác nhận/viết tên bên cạnh vết sửa.",
                "D. Xé bỏ tờ phiếu đó đi và viết lại toàn bộ từ đầu."
            ],
            "answer": [
                2
            ]
        },
        {
            "id": 56,
            "question": "Câu 56: Ai là người chịu trách nhiệm cao nhất về quản lý, điều hành và tổ chức thực hiện các hoạt động điều dưỡng tại một khoa lâm sàng?",
            "options": [
                "A. Bác sĩ điều trị.",
                "B. Điều dưỡng trưởng khoa.",
                "C. Điều dưỡng hành chính khoa.",
                "D. Hộ lý trưởng bệnh viện."
            ],
            "answer": [
                1
            ]
        },
        {
            "id": 57,
            "question": "Câu 57: Hoạt động \"Tư vấn, giáo dục sức khỏe\" cho người bệnh theo Thông tư 31/2021/TT-BYT được thực hiện ở những thời điểm nào?",
            "options": [
                "A. Chỉ thực hiện khi người bệnh chuẩn bị ra viện.",
                "B. Thực hiện xuyên suốt từ khi người bệnh nhập viện, trong quá trình điều trị tại các buồng bệnh và khi người bệnh ra viện.",
                "C. Chỉ thực hiện khi người bệnh yêu cầu và trả phí.",
                "D. Khi khoa phòng vắng người bệnh."
            ],
            "answer": [
                1
            ]
        },
        {
            "id": 58,
            "question": "Câu 58: Việc kiểm kê tủ thuốc trực, tủ vật tư tiêu hao tại khoa lâm sàng thường được quy định thực hiện với tần suất nào để đảm bảo tính sẵn sàng?",
            "options": [
                "A. Kiểm kê hàng ngày vào mỗi ca bàn giao trực hoặc định kỳ hàng tuần/hàng tháng theo quy định cụ thể của bệnh viện.",
                "B. 6 tháng kiểm tra 1 lần.",
                "C. Chỉ kiểm tra khi có đoàn kiểm tra của Bộ Y tế.",
                "D. Khi nào hết thuốc mới kiểm tra."
            ],
            "answer": [
                0
            ]
        },
        {
            "id": 59,
            "question": "Câu 59: Khi phát hiện người bệnh có dấu hiệu trốn viện (không có mặt tại giường bệnh lâu ngày không rõ lý do), điều dưỡng cần báo cáo ngay cho ai để phối hợp xử lý?",
            "options": [
                "A. Báo ngay cho Bác sĩ điều trị, Điều dưỡng trưởng khoa để lập biên bản, báo phòng Kế hoạch tổng hợp và lực lượng Bảo vệ bệnh viện.",
                "B. Không cần làm gì vì đỡ mất công chăm sóc.",
                "C. Gọi điện mắng người nhà người bệnh.",
                "D. Tự ý vứt hết đồ đạc của người bệnh ra ngoài."
            ],
            "answer": [
                0
            ]
        },
        {
            "id": 60,
            "question": "Câu 60: Quy định về trang phục y tế (áo, quần, mũ, biển tên) của điều dưỡng khi làm nhiệm vụ nhằm mục đích chính là gì?",
            "options": [
                "A. Để cho đẹp và đồng bộ.",
                "B. Đảm bảo tính nhận diện rõ ràng chức danh nghề nghiệp, tạo sự chuyên nghiệp, tôn trọng người bệnh và phục vụ công tác kiểm soát nhiễm khuẩn.",
                "C. Để tránh bị lãnh đạo phạt tiền.",
                "D. Để che vết bẩn khi làm việc.\nĐáp án: B\nPHẦN 4: ĐẠO ĐỨC NGHỀ NGHIỆP & GIAO TIẾP ỨNG XỬ (Câu 61 - 80)"
            ],
            "answer": [
                1
            ]
        },
        {
            "id": 61,
            "question": "Câu 61: Theo Thông tư 07/2014/TT-BYT quy định về Quy tắc ứng xử của công chức, viên chức, người lao động tại các cơ sở y tế, khi người bệnh đến khoa nhập viện, thái độ đầu tiên của điều dưỡng là gì?",
            "options": [
                "A. Ngó lơ, bảo họ đứng đợi khi nào gọi tên thì vào.",
                "B. Có thái độ niềm nở, đón tiếp chu đáo, hướng dẫn người bệnh và thân nhân các thủ tục nhập viện, nội quy khoa phòng một cách rõ ràng, dễ hiểu.",
                "C. Yêu cầu nộp tiền tạm ứng ngay lập tức rồi mới nói chuyện.",
                "D. Càu nhàu vì có thêm người bệnh làm tăng khối lượng công việc."
            ],
            "answer": [
                1
            ]
        },
        {
            "id": 62,
            "question": "Câu 62: Khi người nhà người bệnh đang trong tâm trạng bức xúc, nóng nảy và lớn tiếng quát tháo tại phòng hành chính khoa, hành động xử trí nào của điều dưỡng thể hiện sự khéo léo và chuyên nghiệp nhất?",
            "options": [
                "A. Quát lại to hơn để áp đặt sự uy nghiêm của nhân viên y tế.",
                "B. Giữ thái độ bình tĩnh, lắng nghe tích cực, mời họ vào phòng riêng ngồi nói chuyện, giải thích ôn tồn dựa trên quy định và tìm phương án hỗ trợ, nếu vượt thẩm quyền thì báo cáo cấp trên.",
                "C. Bỏ đi chỗ khác không thèm tiếp chuyện.",
                "D. Gọi bảo vệ vào đánh đuổi họ ra ngoài ngay lập tức."
            ],
            "answer": [
                1
            ]
        },
        {
            "id": 63,
            "question": "Câu 63: Nguyên tắc đạo đức \"Tôn trọng quyền tự quyết\" của người bệnh được thể hiện qua hành động nào dưới đây?",
            "options": [
                "A. Ép buộc người bệnh phải dùng dịch vụ kỹ thuật đắt tiền nhất.",
                "B. Cung cấp thông tin đầy đủ, trung thực về các phương pháp chăm sóc, điều trị và tôn trọng lựa chọn đồng ý hoặc từ chối của người bệnh sau khi đã giải thích rõ nguy cơ.",
                "C. Để mặc người bệnh tự truyền dịch lấy nếu họ muốn.",
                "D. Tiết lộ bệnh án của họ cho hàng xóm biết."
            ],
            "answer": [
                1
            ]
        },
        {
            "id": 64,
            "question": "Câu 64: Khi một người bệnh nặng sắp tử vong, ngoài việc thực hiện y lệnh điều trị tích cực, vai trò của điều dưỡng về mặt tâm lý là gì?",
            "options": [
                "A. Tránh mặt không đến buồng bệnh vì sợ cảm giác tang thương.",
                "B. Chăm sóc giảm nhẹ, tạo không gian yên tĩnh, thể hiện sự đồng cảm, an ủi tinh thần người bệnh và thân nhân để họ chuẩn bị tâm lý đón nhận.",
                "C. Nói thẳng với người bệnh là \"Ông/bà sắp chết rồi đấy\".",
                "D. Bảo người nhà đưa về ngay lập tức để đỡ chật giường."
            ],
            "answer": [
                1
            ]
        },
        {
            "id": 65,
            "question": "Câu 65: Hành vi nào sau đây vi phạm nghiêm trọng bí mật thông tin riêng tư của người bệnh?",
            "options": [
                "A. Trao đổi chuyên môn về ca bệnh trong buổi hội chẩn nội bộ giữa các bác sĩ và điều dưỡng của bệnh viện.",
                "B. Chụp ảnh tổn thương vùng kín của người bệnh bằng điện thoại cá nhân rồi đăng lên mạng xã hội kèm tên tuổi người bệnh để \"câu like\".",
                "C. Ghi chép diễn biến bệnh vào hồ sơ bệnh án theo quy định.",
                "D. Báo cáo tình hình dịch bệnh truyền nhiễm cho Trung tâm kiểm soát bệnh tật (CDC) theo luật định."
            ],
            "answer": [
                1
            ]
        },
        {
            "id": 66,
            "question": "Câu 66: Khi người bệnh hỏi điều dưỡng về tác dụng phụ của một loại thuốc họ sắp uống, điều dưỡng nên trả lời như thế nào?",
            "options": [
                "A. Trả lời: \"Tôi chỉ biết phát thuốc, muốn biết gì thì đi hỏi bác sĩ\".",
                "B. Giải thích ngắn gọn, dễ hiểu những tác dụng phụ thường gặp hoặc lưu ý quan trọng khi dùng thuốc (ví dụ: thuốc gây buồn ngủ, nước tiểu đổi màu...) để người bệnh yên tâm phối hợp.",
                "C. Dọa dẫm các tác dụng phụ chết người để người bệnh sợ hãi.",
                "D. Bảo thuốc này hoàn toàn bổ dưỡng, không có bất kỳ tác dụng phụ nào đâu."
            ],
            "answer": [
                1
            ]
        },
        {
            "id": 67,
            "question": "Câu 67: Khái niệm \"Chăm sóc toàn diện\" cho người bệnh có nghĩa là gì?",
            "options": [
                "A. Chỉ thực hiện tiêm và cho uống thuốc đúng giờ.",
                "B. Chăm sóc đáp ứng các nhu cầu về thể chất (điều trị, dinh dưỡng, vệ sinh), tâm lý, xã hội và tinh thần của người bệnh trong suốt quá trình nằm viện.",
                "C. Người bệnh yêu cầu làm gì (kể cả việc riêng cá nhân) điều dưỡng cũng phải làm theo.",
                "D. Chăm sóc cho tất cả mọi người thân đi theo người bệnh."
            ],
            "answer": [
                1
            ]
        },
        {
            "id": 68,
            "question": "Câu 68: Khi nhận được quà biếu bằng tiền mặt trị giá lớn từ người nhà người bệnh với mục đích \"nhờ vả chăm sóc đặc biệt hơn người khác\", điều dưỡng cần xử lý thế nào cho đúng chuẩn mực đạo đức?",
            "options": [
                "A. Vui vẻ nhận ngay và cất vào túi riêng.",
                "B. Từ chối một cách khéo léo, lịch sự; giải thích rõ tinh thần trách nhiệm của nhân viên y tế là chăm sóc công bằng cho tất cả người bệnh và không nhận tiền quà cá nhân.",
                "C. Nhận tiền rồi chia đều cho cả kíp trực.",
                "D. Mắng mỏ người nhà là có ý định hối lộ."
            ],
            "answer": [
                1
            ]
        },
        {
            "id": 69,
            "question": "Câu 69: Khi điều dưỡng vô tình làm rơi một lọ thuốc tiêm của người bệnh xuống đất dẫn đến vỡ lọ thuốc, hành động trung thực và trách nhiệm nhất là gì?",
            "options": [
                "A. Giấu mảnh vỡ đi và đổ lỗi cho người bệnh tự làm vỡ.",
                "B. Báo cáo ngay với Điều dưỡng trưởng và Bác sĩ điều trị để có hướng xử lý bổ sung thuốc kịp thời cho người bệnh, chịu trách nhiệm đền bù lọ thuốc theo quy định nội bộ.",
                "C. Ghi vào phiếu chăm sóc là người bệnh đã được tiêm thuốc như bình thường.",
                "D. Lấy một lọ thuốc của người bệnh khác bù vào mà không báo cáo."
            ],
            "answer": [
                1
            ]
        },
        {
            "id": 70,
            "question": "Câu 70: Trong giao tiếp trực tiếp với người bệnh lớn tuổi, điều dưỡng nên xưng hô như thế nào để thể hiện sự tôn trọng và văn hóa truyền thống?",
            "options": [
                "A. Gọi bằng \"ông\", \"bà\" hoặc \"bác\" kết hợp với tên riêng đầy đủ, xưng \"con\" hoặc \"em/cháu\" phù hợp với lứa tuổi, dùng lời nói dạ thưa lễ phép.",
                "B. Gọi bằng số giường hoặc số phòng (ví dụ: \"Giường 5 kia ra đây uống thuốc\").",
                "C. Xưng hô \"mày - tao\" cho thân mật.",
                "D. Gọi trống không không kèm chủ ngữ."
            ],
            "answer": [
                0
            ]
        },
        {
            "id": 71,
            "question": "Câu 71: Khi thực hiện một kỹ thuật có tính chất gây đau hoặc xâm lấn (như đặt sonde tiểu, thông chọc dịch), hành động giao tiếp cần thiết trước khi làm là gì?",
            "options": [
                "A. Giấu nhẹm đi, lao vào làm luôn để họ không kịp chuẩn bị.",
                "B. Giải thích trước cho người bệnh về mục đích, các bước thực hiện, cảm giác đau có thể gặp và hướng dẫn họ cách hít thở sâu, phối hợp tư thế để giảm đau.",
                "C. Bảo họ không được kêu đau, nếu kêu sẽ dừng không làm nữa.",
                "D. Yêu cầu người nhà ra ngoài và khóa cửa lại chặn tiếng kêu."
            ],
            "answer": [
                1
            ]
        },
        {
            "id": 72,
            "question": "Câu 72: Sự \"Cảm thông\" (Empathy) trong thực hành điều dưỡng được hiểu là gì?",
            "options": [
                "A. Khóc lóc thảm thiết cùng với nỗi đau của người bệnh đến mức bỏ bê công việc.",
                "B. Khả năng đặt mình vào vị trí, hoàn cảnh của người bệnh để hiểu, cảm nhận sâu sắc những đau đớn, lo âu của họ, từ đó đưa ra những hành động chăm sóc nhân văn, phù hợp.",
                "C. Thái độ dửng dưng coi mọi đau đớn của người bệnh là điều đương nhiên.",
                "D. Bố thí tiền bạc cho tất cả người bệnh nghèo."
            ],
            "answer": [
                1
            ]
        },
        {
            "id": 73,
            "question": "Câu 73: Điều gì là KHÔNG ĐÚNG khi điều dưỡng thực hiện kỹ thuật bàn giao thuốc hoặc hướng dẫn người bệnh dùng thuốc tại giường?",
            "options": [
                "A. Kiểm tra danh tính người bệnh trước khi phát.",
                "B. Đưa thuốc qua tay người bệnh rồi quay lưng đi ngay, không cần quan tâm họ có uống hay không.",
                "C. Giải thích cách dùng, liều dùng và tận mắt chứng kiến người bệnh uống thuốc (đối với thuốc uống trực tiếp).",
                "D. Dặn dò các lưu ý khi uống thuốc (uống trước hay sau ăn)."
            ],
            "answer": [
                1
            ]
        },
        {
            "id": 74,
            "question": "Câu 74: Khi đồng nghiệp cùng kíp trực thực hiện sai quy trình chuyên môn (như quên sát khuẩn tay trước khi tiêm), điều dưỡng nên làm gì?",
            "options": [
                "A. Lờ đi coi như không thấy để giữ tình cảm đồng nghiệp.",
                "B. Nhắc nhở tế nhị ngay tại chỗ hoặc hỗ trợ đồng nghiệp sửa sai kịp thời để đảm bảo an toàn tuyệt đối cho người bệnh, tránh phê bình gắt gao trước mặt người bệnh.",
                "C. Chờ đến buổi họp giao ban khoa thì đem ra chỉ trích kịch liệt.",
                "D. Đi nói xấu đồng nghiệp đó với tất cả người bệnh trong phòng."
            ],
            "answer": [
                1
            ]
        },
        {
            "id": 75,
            "question": "Câu 75: Ý nghĩa của việc \"Tôn trọng sự đa dạng văn hóa, tôn giáo\" của người bệnh là gì?",
            "options": [
                "A. Nhân viên y tế ép người bệnh phải theo tôn giáo của mình.",
                "B. Nhân viên y tế tôn trọng các thói quen ăn uống kiêng khem hợp lý, trang phục truyền thống hoặc nhu cầu cầu nguyện tinh thần của người bệnh, miễn là không vi phạm quy định kiểm soát nhiễm khuẩn và an toàn điều trị.",
                "C. Cho phép người bệnh đốt vàng mã ngay tại giường bệnh.",
                "D. Từ chối điều trị cho những người có tôn giáo khác biệt."
            ],
            "answer": [
                1
            ]
        },
        {
            "id": 76,
            "question": "Câu 76: Khi người bệnh hỏi thông tin về một người bệnh khác nằm cùng phòng (ví dụ: \"Ông kia bị bệnh gì mà thấy nặng thế cô?\"), điều dưỡng nên ứng xử thế nào?",
            "options": [
                "A. Kể vanh vách toàn bộ chẩn đoán, hoàn cảnh gia đình của ông kia cho người bệnh này nghe.",
                "B. Lịch sự từ chối và giải thích rằng theo quy định, bệnh viện phải bảo mật thông tin sức khỏe cá nhân của từng người bệnh, mong bác thông cảm.",
                "C. Bảo họ đi mà tự hỏi người ta chứ tôi không biết.",
                "D. Nói dối bừa một bệnh truyền nhiễm nguy hiểm để họ sợ hãi tránh xa."
            ],
            "answer": [
                1
            ]
        },
        {
            "id": 77,
            "question": "Câu 77: Khi có đoàn kiểm tra hoặc khách tham quan vào buồng bệnh, điều dưỡng cần làm gì để bảo vệ sự riêng tư cho người bệnh đang làm thủ thuật bộc lộ thân thể?",
            "options": [
                "A. Mặc kệ cho mọi người tự do nhìn ngó.",
                "B. Kéo rèm che xung quanh giường bệnh hoặc đóng cửa buồng bệnh, tạm hoãn bộc lộ nếu có thể và thông báo lịch sự với đoàn kiểm tra.",
                "C. Quát mắng đoàn kiểm tra đi ra ngoài.",
                "D. Bỏ dở thủ thuật chạy ra ngoài đón tiếp đoàn."
            ],
            "answer": [
                1
            ]
        },
        {
            "id": 78,
            "question": "Câu 78: Hành vi \"Phân biệt đối xử\" đối với người bệnh giàu và người bệnh nghèo vi phạm vào nguyên tắc đạo đức y sinh học nào?",
            "options": [
                "A. Nguyên tắc không gây hại.",
                "B. Nguyên tắc lòng nhân ái.",
                "C. Nguyên tắc công bằng (Justice).",
                "D. Nguyên tắc tôn trọng quyền tự quyết."
            ],
            "answer": [
                2
            ]
        },
        {
            "id": 79,
            "question": "Câu 79: Mục tiêu cốt lõi của phong trào \"Đổi mới phong cách, thái độ phục vụ của hướng tới sự hài lòng của người bệnh\" là gì?",
            "options": [
                "A. Biến người bệnh thành người phục vụ nhân viên y tế.",
                "B. Thay đổi tư duy từ \"ban phát dịch vụ\" sang tư duy \"phục vụ, chăm sóc hướng tới người bệnh là trung tâm\", nâng cao chất lượng dịch vụ y tế.",
                "C. Chỉ để đối phó với các đợt chấm điểm của Bộ Y tế.",
                "D. Nhằm tăng giá viện phí lên cao hơn."
            ],
            "answer": [
                1
            ]
        },
        {
            "id": 80,
            "question": "Câu 80: Khi phát hiện bản thân có một lỗi sai sót chưa gây hậu quả cho người bệnh, phẩm chất đạo đức nào của điều dưỡng được đặt lên hàng đầu?",
            "options": [
                "A. Sự khôn khéo để che giấu lỗi sai.",
                "B. Sự trung thực và lòng tự trọng, chủ động báo cáo ngay để khắc phục nguy cơ sớm nhất vì an toàn của người bệnh.",
                "C. Sự đổ lỗi cho hoàn cảnh quá tải công việc.",
                "D. Sự im lặng chờ đợi xem có ai phát hiện ra không.\nĐáp án: B\nPHẦN 5: KỸ THUẬT ĐIỀU DƯỠNG CƠ BẢN & CẤP CỨU BAN ĐẦU (Câu 81 - 100)"
            ],
            "answer": [
                1
            ]
        },
        {
            "id": 81,
            "question": "Câu 81: Theo Thông tư 51/2017/TT-BYT, thuốc thiết yếu và quan trọng nhất để xử trí cấp cứu phản vệ từ độ II trở lên là gì?",
            "options": [
                "A. Solu-Medrol (Methylprednisolon).",
                "B. Dimedrol (Diphenhydramin).",
                "C. Adrenalin (Epinephrine).",
                "D. Nước muối sinh lý 0,9%."
            ],
            "answer": [
                2
            ]
        },
        {
            "id": 82,
            "question": "Câu 82: Liều lượng Adrenalin tiêm bắp ban đầu cho người lớn khi xác định bị phản vệ độ II trở lên theo phác đồ của Bộ Y tế là bao nhiêu?",
            "options": [
                "A. 1 ống tiêm dưới da.",
                "B. 1/2 ống tiêm bắp (tương đương 0,5 ml dung dịch nồng độ 1mg/1ml).",
                "C. 2 ống tiêm tĩnh mạch trực tiếp.",
                "D. 1/5 ống tiêm bắp."
            ],
            "answer": [
                1
            ]
        },
        {
            "id": 83,
            "question": "Câu 83: Trong quy trình hồi sức tim phổi cơ bản (CPR) cho người lớn bị ngừng tuần hoàn, tỷ lệ giữa số lần ép tim và số lần thổi ngạt (hoặc bóp bóng) khi có 1 hoặc 2 người cứu hộ là bao nhiêu?",
            "options": [
                "A. 15 lần ép tim : 2 lần thổi ngạt.",
                "B. 30 lần ép tim : 2 lần thổi ngạt.",
                "C. 5 lần ép tim : 1 lần thổi ngạt.",
                "D. 30 lần ép tim : 5 lần thổi ngạt."
            ],
            "answer": [
                1
            ]
        },
        {
            "id": 84,
            "question": "Câu 84: Vị trí đặt tay chính xác để thực hiện ép tim ngoài lồng ngực cho người lớn bị ngừng tuần hoàn là ở đâu?",
            "options": [
                "A. Ở nửa trên của xương ức.",
                "B. Ở chính giữa ngực, tức là 1/2 dưới của xương ức.",
                "C. Ở vùng mỏm tim (bên ngực trái).",
                "D. Ở hạ sườn phải."
            ],
            "answer": [
                1
            ]
        },
        {
            "id": 85,
            "question": "Câu 85: Tần số ép tim ngoài lồng ngực chuẩn khi cấp cứu ngừng tuần hoàn cho người lớn là bao nhiêu lần trong một phút?",
            "options": [
                "A. 60 - 80 lần/phút.",
                "B. 80 - 100 lần/phút.",
                "C. 100 - 120 lần/phút.",
                "D. Trên 150 lần/phút."
            ],
            "answer": [
                2
            ]
        },
        {
            "id": 86,
            "question": "Câu 86: Độ sâu chuẩn khi ép tim ngoài lồng ngực cho người lớn để đảm bảo hiệu quả tống máu là bao nhiêu?",
            "options": [
                "A. Khoảng 2 - 3 cm.",
                "B. Khoảng 5 - 6 cm (và đảm bảo lồng ngực nảy lên hoàn toàn sau mỗi lần ép).",
                "C. Càng sâu càng tốt, khoảng 8 - 10 cm.",
                "D. Chỉ cần ép nhẹ trên da ngực."
            ],
            "answer": [
                1
            ]
        },
        {
            "id": 87,
            "question": "Câu 87: Khi đo huyết áp động mạch bằng phương pháp nghe cho người bệnh, tốc độ xả van áp lực của bao đo huyết áp chuẩn là bao nhiêu?",
            "options": [
                "A. Xả thật nhanh để đỡ mất thời gian.",
                "B. Giữ nguyên không xả.",
                "C. Xả từ từ với tốc độ 2 - 3 mmHg mỗi giây.",
                "D. Xả giật cục từng đoạn dài."
            ],
            "answer": [
                2
            ]
        },
        {
            "id": 88,
            "question": "Câu 88: Triệu chứng nào sau đây thuộc tiêu chuẩn chẩn đoán phản vệ Độ I (nhẹ) theo Thông tư 51 của Bộ Y tế?",
            "options": [
                "A. Khó thở, thở rít, tụt huyết áp.",
                "B. Chỉ có triệu chứng ở da, tổ chức dưới da và niêm mạc (như mày đay, ngứa, phù mạch).",
                "C. Đau bụng, nôn mửa, tiêu chảy, co giật.",
                "D. Ngừng tim, ngừng thở."
            ],
            "answer": [
                1
            ]
        },
        {
            "id": 89,
            "question": "Câu 89: Hộp thuốc cấp cứu phản vệ bắt buộc phải có mặt ở những nơi nào trong bệnh viện?",
            "options": [
                "A. Chỉ cần có ở khoa Cấp cứu và phòng Mổ.",
                "B. Có mặt tại tất cả các nơi có tiến hành dùng thuốc, tiêm thuốc, truyền dịch, làm thủ thuật hoặc khám chữa bệnh cho người bệnh.",
                "C. Chỉ có ở xe tiêm của điều dưỡng hành chính.",
                "D. Để tại phòng trực của bác sĩ trực bệnh viện."
            ],
            "answer": [
                1
            ]
        },
        {
            "id": 90,
            "question": "Câu 90: Khi tiến hành cho người bệnh thở oxy qua ống thông mũi hai nhánh (Oxygen cannula), lưu lượng oxy tối đa khuyến cáo nên sử dụng để tránh làm khô niêm mạc và loét mũi là bao nhiêu lít/phút?",
            "options": [
                "A. 1 - 6 lít/phút.",
                "B. 10 - 15 lít/phút.",
                "C. 20 lít/phút.",
                "D. Càng cao càng tốt."
            ],
            "answer": [
                0
            ]
        },
        {
            "id": 91,
            "question": "Câu 91: Kỹ thuật cố định tư thế đầu của người bệnh khi thực hiện đặt ống thông dạ dày (sonde dạ dày) qua đường mũi đúng cách là gì?",
            "options": [
                "A. Ngửa đầu tối đa trong suốt quá trình đặt.",
                "B. Lúc đầu hơi ngửa đầu nhẹ, khi ống vào đến họng (họng sau) thì hướng dẫn người bệnh cúi đầu nhẹ về phía ngực kết hợp động tác nuốt để ống dễ đi vào thực quản.",
                "C. Nghiêng đầu sang bên phải hoàn toàn.",
                "D. Giữ đầu cúi gập mạnh ngay từ đầu."
            ],
            "answer": [
                1
            ]
        },
        {
            "id": 92,
            "question": "Câu 92: Biện pháp nào chính xác nhất giúp điều dưỡng kiểm tra chắc chắn vị trí của ống thông dạ dày đã nằm đúng trong dạ dày trước khi bơm thức ăn/thuốc?",
            "options": [
                "A. Nhìn độ dài của phần ống còn thừa ở ngoài.",
                "B. Dùng bơm tiêm hút thử ra dịch vị (thử giấy quỳ thấy pH axít nhỏ hơn 5), hoặc dùng bơm tiêm bơm khoảng 20ml khí vào ống kết hợp nghe tiếng sục khí ở vùng thượng vị bằng ống nghe.",
                "C. Hỏi người bệnh xem họ thấy ống ở đâu.",
                "D. Thấy người bệnh không ho thì đổ nước vào thử."
            ],
            "answer": [
                1
            ]
        },
        {
            "id": 93,
            "question": "Câu 93: Tai biến nguy hiểm nhất có thể xảy ra khi điều dưỡng bơm thức ăn qua ống thông dạ dày cho người bệnh nằm ngửa, tri giác giảm mà không nâng cao đầu là gì?",
            "options": [
                "A. Chướng bụng đầy hơi.",
                "B. Trào ngược dịch dạ dày gây sặc vào đường thở dẫn đến suy hô hấp, viêm phổi hít.",
                "C. Người bệnh bị đi ngoài phân lỏng.",
                "D. Tuột ống thông ra ngoài."
            ],
            "answer": [
                1
            ]
        },
        {
            "id": 94,
            "question": "Câu 94: Khi thực hiện kỹ thuật đặt ống thông tiểu (sonde tiểu) lưu cho người bệnh, sau khi đưa ống vào thấy có nước tiểu chảy ra, điều dưỡng cần đẩy thêm ống vào trong bao nhiêu cm trước khi bơm bóng chèn cố định?",
            "options": [
                "A. Không cần đẩy thêm, bơm luôn tại chỗ.",
                "B. Đẩy thêm vào khoảng 3 - 5 cm để đảm bảo bóng chèn đã nằm hoàn toàn trong lòng bàng quang, tránh bơm bóng làm rách niệu đạo.",
                "C. Đẩy hết toàn bộ chiều dài của ống thông.",
                "D. Rút bớt ống ra ngoài rồi mới bơm bóng."
            ],
            "answer": [
                1
            ]
        },
        {
            "id": 95,
            "question": "Câu 95: Vị trí treo túi đựng nước tiểu của người bệnh có đặt ống thông tiểu lưu phải đảm bảo nguyên tắc nào để phòng chống nhiễm khuẩn ngược dòng?",
            "options": [
                "A. Treo cao hơn vị trí bàng quang của người bệnh.",
                "B. Đặt trực tiếp túi nước tiểu nằm bệt dưới nền nhà.",
                "C. Treo thấp hơn vị trí bàng quang của người bệnh khoảng 50cm và không chạm đất.",
                "D. Đặt lên trên bụng người bệnh cho gọn."
            ],
            "answer": [
                2
            ]
        },
        {
            "id": 96,
            "question": "Câu 96: Tần suất thay vị trí cố định băng dính/kim luồn ngoại vi (đường truyền tĩnh mạch) cho người bệnh truyền dịch kéo dài tối đa thông thường là bao lâu để phòng viêm tắc tĩnh mạch?",
            "options": [
                "A. Mỗi ngày thay 1 lần.",
                "B. Khoảng mỗi 72 đến 96 giờ (3 - 4 ngày), hoặc thay ngay khi có dấu hiệu sưng, đỏ, đau, nhiễm khuẩn tại vị trí tiêm.",
                "C. Giữ nguyên cho đến khi người bệnh ra viện không cần thay.",
                "D. 2 tuần thay 1 lần."
            ],
            "answer": [
                1
            ]
        },
        {
            "id": 97,
            "question": "Câu 97: Khi đếm nhịp thở của người bệnh, để có kết quả chính xác và khách quan nhất, điều dưỡng nên áp dụng mẹo kỹ thuật nào?",
            "options": [
                "A. Nói cho người bệnh biết là \"Tôi chuẩn bị đếm nhịp thở của bác nhé\".",
                "B. Đếm nhịp thở ngay sau khi người bệnh vừa chạy bộ hoặc vừa khóc xong.",
                "C. Giữ tay trên cổ tay người bệnh như đang bắt mạch, mắt âm thầm quan sát sự di động của lồng ngực/bụng người bệnh trong trọn vẹn 1 phút để họ không tự ý thay đổi nhịp thở.",
                "D. Chỉ cần nhìn qua khoảng 5 giây rồi nhân số lần lên."
            ],
            "answer": [
                2
            ]
        },
        {
            "id": 98,
            "question": "Câu 98: Khi thực hiện kỹ thuật tiêm dưới da (ví dụ tiêm Insulin), góc độ đâm kim chuẩn so với mặt da thường là bao nhiêu độ?",
            "options": [
                "A. Góc 10 - 15 độ.",
                "B. Góc 30 - 45 độ (hoặc 90 độ tùy thuộc vào độ dày lớp mỡ dưới da và độ dài kim tiêm).",
                "C. Góc 90 độ hoàn toàn bằng kim dài 5cm.",
                "D. Đâm kim song song sát mặt da."
            ],
            "answer": [
                1
            ]
        },
        {
            "id": 99,
            "question": "Câu 99: Trước khi tiến hành truyền dịch cho người bệnh, bước \"đuổi khí\" trong dây truyền dịch có mục đích quan trọng nhất là gì?",
            "options": [
                "A. Để dịch truyền chảy nhanh hơn.",
                "B. Để loại bỏ hoàn toàn các bong bóng khí trong lòng dây truyền, ngăn ngừa tai biến tắc mạch do khí cực kỳ nguy hiểm cho tính mạng người bệnh.",
                "C. Để làm mát dịch truyền.",
                "D. Để làm sạch lòng dây truyền."
            ],
            "answer": [
                1
            ]
        },
        {
            "id": 100,
            "question": "Câu 100: Khi người bệnh đang truyền dịch bỗng xuất hiện triệu chứng rét run lập cập, sốt cao, vã mồ hôi, mạch nhanh, hành động xử trí khẩn cấp và đúng trình tự nhất của điều dưỡng là gì?",
            "options": [
                "A. Đắp thêm chăn ấm cho người bệnh và tăng tốc độ truyền dịch cho nhanh hết.",
                "B. Tắt dịch truyền ngay lập tức (giữ nguyên đường truyền), báo ngay cho bác sĩ điều trị, thực hiện y lệnh cấp cứu, đo lại dấu hiệu sinh tồn và theo dõi sát người bệnh.",
                "C. Rút kim truyền vứt đi ngay và bảo người nhà đưa người bệnh sang khoa khác.",
                "D. Cho người bệnh uống ngay một viên thuốc hạ sốt rồi đi làm việc khác."
            ],
            "answer": [
                1
            ]
        }
    ]
}